fenix/__init__.py
fenix/cli/__init__.py
fenix/cli/main.py
fenix/cli/commands/__init__.py
fenix/cli/commands/help.py
fenix/cli/commands/make.py
fenix/cli/commands/run.py
fenix/cli/commands/version.py
fenix/config/__init__.py
fenix/config/default.py
fenix/config/settings.py
fenix/core/__init__.py
fenix/core/server.py
fenix/extensions/__init__.py
fenix/templating/__init__.py
fenix/templating/engine.py
fenix/utils/__init__.py
fenix/utils/common.py
pyfenix-0.1.5.dist-info/METADATA
pyfenix-0.1.5.dist-info/WHEEL
pyfenix-0.1.5.dist-info/entry_points.txt
pyfenix-0.1.5.dist-info/top_level.txt
pyfenix-0.1.5.dist-info/RECORD
