Metadata-Version: 2.4
Name: pyfenix
Version: 0.1.5
Summary: A blazing fast and minimal Python full-stack web framework
Home-page: https://github.com/tinprogrammers/FeniX
Author: Azeem Teli
Author-email: tinprogrammers@gmail.com
License: MIT
Project-URL: Documentation, https://github.com/tinprogrammers/FeniX#readme
Project-URL: Source, https://github.com/tinprogrammers/FeniX
Project-URL: Issue Tracker, https://github.com/tinprogrammers/FeniX/issues
Project-URL: Changelog, https://github.com/tinprogrammers/FeniX/releases
Keywords: python web framework minimal fast cli full-stack fenix
Platform: any
Classifier: Development Status :: 3 - Alpha
Classifier: Intended Audience :: Developers
Classifier: Programming Language :: Python :: 3
Classifier: Framework :: Flask
Classifier: License :: OSI Approved :: MIT License
Classifier: Operating System :: OS Independent
Requires-Python: >=3.7
Requires-Dist: rich>=13.0.0
Dynamic: author
Dynamic: author-email
Dynamic: classifier
Dynamic: description
Dynamic: description-content-type
Dynamic: home-page
Dynamic: keywords
Dynamic: license
Dynamic: platform
Dynamic: project-url
Dynamic: requires-dist
Dynamic: requires-python
Dynamic: summary
